asunder/__init__.py
asunder/__main__.py
asunder/_version.py
asunder/analyze/__init__.py
asunder/analyze/chrun.py
asunder/analyze/maintainability.py
asunder/command/__init__.py
asunder/command/cli.py
asunder/command/rename_cmd.py
asunder/project/__init__.py
asunder/project/project.py
asunder/rope_sdk/__init__.py
asunder/rope_sdk/find/__init__.py
asunder/rope_sdk/find/find.py
asunder/rope_sdk/refactor/__init__.py
asunder/rope_sdk/refactor/move/__init__.py
asunder/rope_sdk/refactor/move/move.py
asunder/rope_sdk/refactor/rename/__init__.py
asunder/rope_sdk/refactor/rename/rename.py
asunder/utils/__init__.py
asunder/utils/logging.py
asunder-0.1.0.dist-info/entry_points.txt
asunder-0.1.0.dist-info/LICENSE
asunder-0.1.0.dist-info/WHEEL
asunder-0.1.0.dist-info/METADATA
asunder-0.1.0.dist-info/RECORD
