Metadata-Version: 2.1
Name: asunder
Version: 0.1.0
Summary: CLI for refactoring python projects
Author: Leandro G. Almeida
Author-email: leandro.g.almeida@gmail.com
Requires-Python: >=3.10,<4.0
Classifier: Programming Language :: Python :: 3
Classifier: Programming Language :: Python :: 3.10
Classifier: Programming Language :: Python :: 3.11
Requires-Dist: rich (>=12.6.0,<13.0.0)
Requires-Dist: rope (>=1.4.0,<2.0.0)
Requires-Dist: typer (>=0.7.0,<0.8.0)
